kt2/__init__.py
kt2/cli.py
kt2/client.py
kt2/commands.py
kt2/errors.py
kt2/helpers.py
kt2/jwks.py
kt2/logging.py
kt2/models.py
kt2/oauth.py
kt2/py.typed
kt2/settings.py
kt2/types.py
kt2/utils.py
kt2-0.0.19a0.dist-info/entry_points.txt
kt2-0.0.19a0.dist-info/LICENSE
kt2-0.0.19a0.dist-info/WHEEL
kt2-0.0.19a0.dist-info/METADATA
kt2-0.0.19a0.dist-info/RECORD
