Metadata-Version: 2.1
Name: kt2
Version: 0.0.19a0
Summary: koppeltaal 
Author-email: TK <tk@terminalkitten.com>
Classifier: License :: OSI Approved :: MIT License
Requires-Dist: pydantic==1.10.12
Requires-Dist: click
Requires-Dist: httpx
Requires-Dist: pyfiglet
Requires-Dist: rich
Requires-Dist: toml
Requires-Dist: fhir.resources
Requires-Dist: black ; extra == "dev"
Requires-Dist: devtools ; extra == "dev"
Requires-Dist: ipdb ; extra == "dev"
Requires-Dist: ipython ; extra == "dev"
Requires-Dist: flit ; extra == "dev"
Requires-Dist: ruff ; extra == "dev"
Requires-Dist: isort ; extra == "dev"
Requires-Dist: wheel ; extra == "dev"
Requires-Dist: rich ; extra == "dev"
Requires-Dist: pdoc3 ; extra == "doc"
Project-URL: Home, https://github.com/terminalkitten/kt2
Provides-Extra: dev
Provides-Extra: doc
